range_ops/__init__.py
range_ops/rangers.py
range_ops-0.0.1.dist-info/METADATA
range_ops-0.0.1.dist-info/WHEEL
range_ops-0.0.1.dist-info/licenses/LICENCE
range_ops-0.0.1.dist-info/RECORD
