Metadata-Version: 2.1
Name: range_ops
Version: 0.0.1
Summary: simplify combining and comparing contiguous ranges of int/floats
Author-email: Tom Shaw <teshaw@live.co.uk>
License-File: LICENCE
Classifier: License :: OSI Approved :: MIT License
Classifier: Operating System :: OS Independent
Classifier: Programming Language :: Python :: 3
Requires-Python: >=3.8
Requires-Dist: pandas
